propagate_uncertainties/__init__.py
propagate_uncertainties/version.py
propagate_uncertainties_sebastian_achim_mueller-0.2.6.dist-info/licenses/LICENSE
propagate_uncertainties_sebastian_achim_mueller-0.2.6.dist-info/METADATA
propagate_uncertainties_sebastian_achim_mueller-0.2.6.dist-info/WHEEL
propagate_uncertainties_sebastian_achim_mueller-0.2.6.dist-info/top_level.txt
propagate_uncertainties_sebastian_achim_mueller-0.2.6.dist-info/RECORD
