Metadata-Version: 2.4
Name: propagate_uncertainties_sebastian-achim-mueller
Version: 0.2.6
Summary: Propagate the uncertainty of multiple values
Home-page: https://github.com/cherenkov-plenoscope/propagate_uncertainties
Author: Sebastian Achim Mueller
Author-email: sebastian-achim.mueller@mpi-hd.mpg.de
Classifier: Programming Language :: Python :: 3
Classifier: License :: OSI Approved :: MIT License
Classifier: Operating System :: OS Independent
Classifier: Natural Language :: English
Classifier: Intended Audience :: Science/Research
License-File: LICENSE
Dynamic: author
Dynamic: author-email
Dynamic: classifier
Dynamic: description
Dynamic: description-content-type
Dynamic: home-page
Dynamic: license-file
Dynamic: summary
